napari_roi_registration/__init__.py
napari_roi_registration/_version.py
napari_roi_registration/_widget.py
napari_roi_registration/binary_image.png
napari_roi_registration/napari.yaml
napari_roi_registration/registration_utils.py
napari_roi_registration/_tests/__init__.py
napari_roi_registration/_tests/test_widget.py
napari_roi_registration-0.1.4.dist-info/LICENSE
napari_roi_registration-0.1.4.dist-info/METADATA
napari_roi_registration-0.1.4.dist-info/WHEEL
napari_roi_registration-0.1.4.dist-info/entry_points.txt
napari_roi_registration-0.1.4.dist-info/top_level.txt
napari_roi_registration-0.1.4.dist-info/RECORD
