Metadata-Version: 2.1
Name: napari-roi-registration
Version: 0.1.4
Summary: A plugin to perform registration of regions-of-interests in time-lapse data.
Home-page: https://github.com/GiorgiaTortora/napari-roi-registration
Author: Andrea Bassi and Giorgia Tortora
Author-email: giorgia.tortora@polimi.it
License: BSD-3-Clause
Project-URL: Bug Tracker, https://github.com/GiorgiaTortora/napari-roi-registration/issues
Project-URL: Documentation, https://github.com/GiorgiaTortora/napari-roi-registration#README.md
Project-URL: Source Code, https://github.com/GiorgiaTortora/napari-roi-registration
Project-URL: User Support, https://github.com/GiorgiaTortora/napari-roi-registration/issues
Classifier: Development Status :: 2 - Pre-Alpha
Classifier: Intended Audience :: Developers
Classifier: Framework :: napari
Classifier: Topic :: Software Development :: Testing
Classifier: Programming Language :: Python
Classifier: Programming Language :: Python :: 3
Classifier: Programming Language :: Python :: 3.8
Classifier: Programming Language :: Python :: 3.9
Classifier: Programming Language :: Python :: 3.10
Classifier: Operating System :: OS Independent
Classifier: License :: OSI Approved :: BSD License
Requires-Python: >=3.8
License-File: LICENSE
Requires-Dist: numpy
Requires-Dist: magicgui
Requires-Dist: qtpy
Requires-Dist: scikit-image
Requires-Dist: opencv-python
Requires-Dist: matplotlib
Requires-Dist: openpyxl
Provides-Extra: testing
Requires-Dist: tox ; extra == 'testing'
Requires-Dist: pytest ; extra == 'testing'
Requires-Dist: pytest-cov ; extra == 'testing'
Requires-Dist: pytest-qt ; extra == 'testing'
Requires-Dist: napari ; extra == 'testing'
Requires-Dist: pyqt5 ; extra == 'testing'
Requires-Dist: scikit-image ; extra == 'testing'
Requires-Dist: opencv-python-headless ; extra == 'testing'
Requires-Dist: matplotlib ; extra == 'testing'
Requires-Dist: openpyxl ; extra == 'testing'
